pypwt/__init__.py
pypwt/io.py
pypwt/pwt.py
pypwt/sandbox.py
pypwt/test/__init__.py
pypwt/test/test_pwt.py
pypwt-0.1.1.dist-info/DESCRIPTION.rst
pypwt-0.1.1.dist-info/METADATA
pypwt-0.1.1.dist-info/metadata.json
pypwt-0.1.1.dist-info/RECORD
pypwt-0.1.1.dist-info/top_level.txt
pypwt-0.1.1.dist-info/WHEEL
