Metadata-Version: 2.0
Name: pypwt
Version: 0.1.1
Summary: Python package for generating the Penn World Tables data set.
Home-page: https://github.com/davidrpugh/penn-world-tables
Author: David R. Pugh
Author-email: david.pugh@maths.ox.ac.uk
License: LICENSE.txt
Platform: UNKNOWN
Classifier: Development Status :: 1 - Planning
Classifier: Intended Audience :: Education
Classifier: Intended Audience :: Science/Research
Classifier: License :: OSI Approved :: MIT License
Classifier: Operating System :: OS Independent
Classifier: Programming Language :: Python
Requires-Dist: pandas
